[
  {
    "course_id": "UXD001",
    "title": "User Experience Design Essentials - Adobe XD UI UX Design",
    "instructor": "Kevin Perry",
    "category_id": 10,
    "category_name": "Web Development",
    "last_updated": "04 April, 2022",
    "rating": 4.86,
    "reviews_count": 88,
    "price": 90.00,
    "original_price": 120.00,
    "lessons": 8,
    "duration": "15h 30m 36s",
    "level": "Beginners",
    "language": "English",
    "quizzes": 0,
    "tags": ["Best Seller", "Latest"],
    "description": "Learn to produce practical and effective User Experience (UX) and User Interface (UI) designs using Adobe XD. Follow along with real-life freelance project files to create high quality, functional mockups, test on mobile devices, and prepare assets for developers."
  },
  {
    "course_id": "CS002",
    "title": "Introduction to Python Programming and Data Structures",
    "instructor": "Dr. Anya Sharma",
    "category_id": 7,
    "category_name": "Computer Science",
    "last_updated": "10 October, 2023",
    "rating": 4.75,
    "reviews_count": 1200,
    "price": 75.00,
    "original_price": 100.00,
    "lessons": 15,
    "duration": "22h 45m 00s",
    "level": "Beginners",
    "language": "English",
    "quizzes": 5,
    "tags": ["Popular"]
  },
  {
    "course_id": "MKT003",
    "title": "Digital Marketing Masterclass: SEO, Social Media, and Analytics",
    "instructor": "Sarah Chen",
    "category_id": 5,
    "category_name": "Marketing",
    "last_updated": "25 January, 2024",
    "rating": 4.91,
    "reviews_count": 950,
    "price": 110.00,
    "original_price": 150.00,
    "lessons": 20,
    "duration": "30h 00m 00s",
    "level": "All Levels",
    "language": "English",
    "quizzes": 8,
    "tags": ["Latest", "Best Seller"]
  },
  {
    "course_id": "ART004",
    "title": "Oil Painting Techniques: Mastering Portraits",
    "instructor": "Marco Rossi",
    "category_id": 2,
    "category_name": "Arts & Design",
    "last_updated": "01 March, 2023",
    "rating": 4.55,
    "reviews_count": 520,
    "price": 60.00,
    "original_price": 80.00,
    "lessons": 12,
    "duration": "18h 15m 30s",
    "level": "Intermediate",
    "language": "English",
    "quizzes": 0,
    "tags": ["Highly Rated"]
  },
  {
    "course_id": "FIN005",
    "title": "Financial Modeling and Valuation Analyst (FMVA)",
    "instructor": "Global Finance Team",
    "category_id": 6,
    "category_name": "Business & Finance",
    "last_updated": "15 November, 2024",
    "rating": 4.88,
    "reviews_count": 1800,
    "price": 150.00,
    "original_price": 200.00,
    "lessons": 25,
    "duration": "45h 00m 00s",
    "level": "Advanced",
    "language": "English",
    "quizzes": 10,
    "tags": ["Certification"]
  },
  {
    "course_id": "HEALTH006",
    "title": "Certified Personal Trainer (CPT) Preparation Course",
    "instructor": "Fitness Experts Inc.",
    "category_id": 4,
    "category_name": "Health & Fitness",
    "last_updated": "20 February, 2024",
    "rating": 4.62,
    "reviews_count": 780,
    "price": 95.00,
    "original_price": 125.00,
    "lessons": 18,
    "duration": "35h 20m 00s",
    "level": "Beginners",
    "language": "English",
    "quizzes": 6,
    "tags": ["Best Seller"]
  },
  {
    "course_id": "DS007",
    "title": "Data Science with R: Statistical Analysis and Visualization",
    "instructor": "Professor David Lee",
    "category_id": 9,
    "category_name": "Data Science",
    "last_updated": "05 September, 2023",
    "rating": 4.70,
    "reviews_count": 1100,
    "price": 85.00,
    "original_price": 115.00,
    "lessons": 16,
    "duration": "28h 00m 00s",
    "level": "Intermediate",
    "language": "English",
    "quizzes": 7,
    "tags": ["Popular"]
  },
  {
    "course_id": "VID008",
    "title": "Cinematography Fundamentals: Lighting and Composition",
    "instructor": "Eliza Thorne",
    "category_id": 8,
    "category_name": "Video & Photography",
    "last_updated": "12 December, 2023",
    "rating": 4.80,
    "reviews_count": 650,
    "price": 70.00,
    "original_price": 90.00,
    "lessons": 10,
    "duration": "14h 50m 00s",
    "level": "Beginners",
    "language": "English",
    "quizzes": 4,
    "tags": ["Short Course"]
  },
  {
    "course_id": "BUS009",
    "title": "Foundations of Project Management (PMP Prep)",
    "instructor": "Robert Green",
    "category_id": 1,
    "category_name": "Business Management",
    "last_updated": "08 April, 2024",
    "rating": 4.78,
    "reviews_count": 1500,
    "price": 120.00,
    "original_price": 160.00,
    "lessons": 22,
    "duration": "40h 00m 00s",
    "level": "All Levels",
    "language": "English",
    "quizzes": 9,
    "tags": ["Certification", "Latest"],
    "description": "Master the principles, tools, and techniques for successful project management, covering the PMBOK® guide structure and preparing you for the PMP certification exam."
  },
  {
    "course_id": "PD010",
    "title": "The Science of Habit Building and Productivity",
    "instructor": "Maya Patel",
    "category_id": 3,
    "category_name": "Personal Development",
    "last_updated": "01 January, 2024",
    "rating": 4.68,
    "reviews_count": 890,
    "price": 55.00,
    "original_price": 75.00,
    "lessons": 7,
    "duration": "10h 45m 00s",
    "level": "Beginners",
    "language": "English",
    "quizzes": 3,
    "tags": ["Quick Learning", "Popular"],
    "description": "A practical course focused on leveraging psychological research to build lasting positive habits, break bad ones, and maximize personal and professional productivity."
  }
]